README.rst
setup.py
usergrid/UsergridApplication.py
usergrid/UsergridAuth.py
usergrid/UsergridClient.py
usergrid/UsergridCollection.py
usergrid/UsergridConnection.py
usergrid/UsergridError.py
usergrid/UsergridHelpers.py
usergrid/UsergridOrganization.py
usergrid/UsergridQueryIterator.py
usergrid/__init__.py
usergrid/app_templates.py
usergrid/management_templates.py
usergrid.egg-info/PKG-INFO
usergrid.egg-info/SOURCES.txt
usergrid.egg-info/dependency_links.txt
usergrid.egg-info/requires.txt
usergrid.egg-info/top_level.txt