Metadata-Version: 1.1
Name: usergrid
Version: 0.2.10
Summary: Usergrid SDK for Python
Home-page: http://usergrid.apache.org
Author: Jeff West
Author-email: jwest@apigee.com
License: UNKNOWN
Download-URL: https://codeload.github.com/jwest-apigee/usergrid-python/zip/v0.2.10
Platform: UNKNOWN
Classifier: Development Status :: 4 - Beta
Classifier: Intended Audience :: Developers
Classifier: Operating System :: OS Independent
Classifier: Topic :: Software Development
